elk/__init__.py
elk/__main__.py
elk/debug_logging.py
elk/files.py
elk/parsing.py
elk/run.py
elk/truncated_eigh.py
elk/evaluation/__init__.py
elk/evaluation/evaluate.py
elk/extraction/__init__.py
elk/extraction/balanced_sampler.py
elk/extraction/dataset_name.py
elk/extraction/extraction.py
elk/extraction/generator.py
elk/extraction/prompt_dataset.py
elk/extraction/prompt_loading.py
elk/metrics/__init__.py
elk/metrics/accuracy.py
elk/metrics/calibration.py
elk/metrics/eval.py
elk/metrics/roc_auc.py
elk/plotting/command.py
elk/plotting/visualize.py
elk/promptsource/__init__.py
elk/promptsource/templates.py
elk/promptsource/templates/Zaid/coqa_expanded/templates.yaml
elk/promptsource/templates/Zaid/quac_expanded/templates.yaml
elk/promptsource/templates/acronym_identification/templates.yaml
elk/promptsource/templates/ade_corpus_v2/Ade_corpus_v2_classification/templates.yaml
elk/promptsource/templates/ade_corpus_v2/Ade_corpus_v2_drug_ade_relation/templates.yaml
elk/promptsource/templates/ade_corpus_v2/Ade_corpus_v2_drug_dosage_relation/templates.yaml
elk/promptsource/templates/adversarial_qa/adversarialQA/templates.yaml
elk/promptsource/templates/adversarial_qa/dbert/templates.yaml
elk/promptsource/templates/adversarial_qa/dbidaf/templates.yaml
elk/promptsource/templates/adversarial_qa/droberta/templates.yaml
elk/promptsource/templates/aeslc/templates.yaml
elk/promptsource/templates/ag_news/templates.yaml
elk/promptsource/templates/ai2_arc/ARC-Challenge/templates.yaml
elk/promptsource/templates/ai2_arc/ARC-Easy/templates.yaml
elk/promptsource/templates/amazon_polarity/templates.yaml
elk/promptsource/templates/amazon_reviews_multi/en/templates.yaml
elk/promptsource/templates/amazon_us_reviews/Wireless_v1_00/templates.yaml
elk/promptsource/templates/ambig_qa/light/templates.yaml
elk/promptsource/templates/anli/templates.yaml
elk/promptsource/templates/app_reviews/templates.yaml
elk/promptsource/templates/aqua_rat/raw/templates.yaml
eleuther_elk-0.1.1.dist-info/LICENSE.md
eleuther_elk-0.1.1.dist-info/METADATA
eleuther_elk-0.1.1.dist-info/WHEEL
eleuther_elk-0.1.1.dist-info/entry_points.txt
eleuther_elk-0.1.1.dist-info/top_level.txt
eleuther_elk-0.1.1.dist-info/RECORD
