Metadata-Version: 2.1
Name: eleuther-elk
Version: 0.1.1
Summary: Keeping language models honest by directly eliciting knowledge encoded in their activations
License: MIT License
Keywords: nlp,interpretability,language-models,explainable-ai
Requires-Python: >=3.10
License-File: LICENSE.md
Requires-Dist: accelerate
Requires-Dist: concept-erasure (==0.1.0)
Requires-Dist: datasets (>=2.9.0)
Requires-Dist: einops
Requires-Dist: numpy (>=1.20.0)
Requires-Dist: pandas
Requires-Dist: pynvml
Requires-Dist: simple-parsing (>=0.1.1)
Requires-Dist: torch (>=1.11.0)
Requires-Dist: tqdm (>=4.0.0)
Requires-Dist: transformers (>=4.0.0)
Requires-Dist: jinja2
Requires-Dist: plotly (==5.14.1)
Requires-Dist: kaleido (==0.2.1)
Requires-Dist: rich (==13.3.5)
Provides-Extra: 8bit
Requires-Dist: bitsandbytes ; extra == '8bit'
Provides-Extra: dev
Requires-Dist: hypothesis ; extra == 'dev'
Requires-Dist: pre-commit ; extra == 'dev'
Requires-Dist: pytest ; extra == 'dev'
Requires-Dist: pyright (==1.1.304) ; extra == 'dev'
Requires-Dist: scikit-learn ; extra == 'dev'
Requires-Dist: pyfakefs ; extra == 'dev'
